<?xml-model href="../schema/sourceDesc_fragment.rnc" type="application/relax-ng-compact-syntax"?>
<sourceDesc xmlns="http://www.tei-c.org/ns/1.0">
   <biblFull>
      <titleStmt>
         <title>Great Britaine, all in blacke for the incomparable losse of Henry, our late worthy prince / by John Taylor.</title>
         <author>Taylor, John, 1580-1653.</author>
         <author>Rowley, William, 1585?-1642?</author>
      </titleStmt>
      <extent>[24] p. : port.  </extent>
      <publicationStmt>
         <publisher>Printed by <persName type="printer">E.A.</persName> for <persName type="publisher">I. Wright</persName> dwelling in <placeName>Newgate Market, neere vnto Christs Church gate</placeName>,</publisher><pubPlace>London :</pubPlace>
         <date>1612.</date>
      </publicationStmt>
      <notesStmt>
         <note>In verse.</note>
         <note>"To the publique reader" and the following poem by William Rowley: p. [19]-[24].</note>
         <note>Signatures: A-C&#8308;.</note>
         <note>Title in black border.</note>
         <note>Reproduction of original in the Harvard University. Library.</note>
      </notesStmt>
   </biblFull>
<listPerson><person type="publisher"><persName>I. Wright</persName></person><person type="printer"><persName>E.A.</persName></person></listPerson><listPlace><place type="location"><placeName>Newgate Market, neere vnto Christs Church gate</placeName></place></listPlace></sourceDesc>
