<?xml-model href="../schema/sourceDesc_fragment.rnc" type="application/relax-ng-compact-syntax"?>
<sourceDesc xmlns="http://www.tei-c.org/ns/1.0">
  <biblFull>
    <titleStmt>
      <title>A three-fold cord to unite soules for ever unto God. 1. The mysterie of godlinesse opened. 2. The imitation of Christ proposed. 3. The crowne of afflicted saints promised. / As it was compacted by M. Richard Head, M.A. and sometimes minister of the Gospel, in his labours at Great Torrington in Devon. Published now, after his death, for publike profit.</title>
      <author>Head, Richard, Rev.</author>
    </titleStmt>
    <extent>[4], 50 p.   </extent>
    <publicationStmt>
      <publisher>Printed by <persName type="printer">E.P.</persName> for <persName type="publisher">Fr. Coles</persName>, and are to be sold at <placeName>his shop in the Old-Bayly, at the Signe of the Halfe-Bowle</placeName>,</publisher>
      <pubPlace>London :</pubPlace>
      <date>1647.</date>
    </publicationStmt>
    <notesStmt>
      <note>The words "1. The mysterie .. promised." are bracketed together on title page.</note>
      <note>Annotation on Thomason copy: "8ber [i.e. October] 10".</note>
      <note>Reproduction of the original in the British Library.</note>
      <note>The saints inheritance -- The mysterie of Godlinesse -- The reward of imitation.</note>
    </notesStmt>
  </biblFull>
  <listPerson>
    <person type="publisher">
      <persName>Fr. Coles</persName>
    </person>
    <person type="printer">
      <persName>E.P.</persName>
    </person>
  </listPerson>
  <listPlace>
    <place type="location">
      <placeName>his shop in the Old-Bayly, at the Signe of the Halfe-Bowle</placeName>
    </place>
  </listPlace>
</sourceDesc>
