<?xml-model href="../schema/sourceDesc_fragment.rnc" type="application/relax-ng-compact-syntax"?>
<sourceDesc xmlns="http://www.tei-c.org/ns/1.0">
  <biblFull>
    <titleStmt>
      <title>An holy panegyrick a sermon preached at Paules Crosse vpon the anniuersarie solemnitie of the happie inauguration of our dread soueraigne Lord King James, Mar. 24, 1613 / by J.H.D.D.</title>
      <author>Hall, Joseph, 1574-1656.</author>
    </titleStmt>
    <extent>[6], 109 p.   </extent>
    <publicationStmt>
      <publisher>Printed by <persName type="printer">Iohn Pindley</persName> for <persName type="publisher">Samuel Macham</persName>,</publisher>
      <pubPlace>London :</pubPlace>
      <date when="1613">1613.</date>
    </publicationStmt>
    <notesStmt>
      <note>Signatures: A&#8308;(-A1) B-G&#8312; H&#8311;.</note>
      <note>Title within architectural border.</note>
      <note>Imperfect: print show-through.</note>
      <note>Reproduction of original in the Harvard University. Library.</note>
      <note>Includes bibliographical references.</note>
    </notesStmt>
  </biblFull>
  <listPerson>
    <person type="publisher">
      <persName>Samuel Macham</persName>
    </person>
    <person type="printer">
      <persName>Iohn Pindley</persName>
    </person>
  </listPerson>
</sourceDesc>
