<?xml-model href="../schema/sourceDesc_fragment.rnc" type="application/relax-ng-compact-syntax"?>
<sourceDesc xmlns="http://www.tei-c.org/ns/1.0">
   <biblFull>
      <titleStmt>
         <title>Here after foloweth the newe pryuyleges and indulge[n]ces graunted by our holy Father the Pope Leo.x. to the house of seynt Thomas of Acres in London</title>
         <author>St. Thomas's Hospital (London, England)</author>
         <author>Catholic Church. aut</author>
      </titleStmt>
      <extent>1 sheet ([1] p.)   </extent>
      <publicationStmt>
         <publisher>Richard Pynson,</publisher>
         <pubPlace>[London :</pubPlace>
         <date when="1517" cert="low">1517?]</date>
      </publicationStmt>
      <notesStmt>
         <note>Imprint from STC.</note>
         <note>List of indulgences granted to the confraternity--STC.</note>
         <note>Formerly STC 15474.</note>
         <note>Identified as STC 15474 on UMI microfilm.</note>
         <note>Imperfect: torn through middle, affecting text.</note>
         <note>Reproduction of the original in the British Library.</note>
      </notesStmt>
   </biblFull>
</sourceDesc>
