<?xml-model href="../schema/sourceDesc_fragment.rnc" type="application/relax-ng-compact-syntax"?>
<sourceDesc xmlns="http://www.tei-c.org/ns/1.0">
  <biblFull>
    <titleStmt>
      <title>A narrative of the cause and manner of the imprisonment of the lords now close prisoners in the Tower of London.</title>
      <author>J. E.</author>
    </titleStmt>
    <extent>26 p.   </extent>
    <publicationStmt>
      <publisher>[s.n.],</publisher>
      <pubPlace>Amsterdam :</pubPlace>
      <date when="1677">1677.</date>
    </publicationStmt>
    <notesStmt>
      <note>Signed: J. E.</note>
      <note>Reproduction of original in Huntington Library.</note>
    </notesStmt>
  </biblFull>
</sourceDesc>
