<?xml-model href="../schema/sourceDesc_fragment.rnc" type="application/relax-ng-compact-syntax"?>
<sourceDesc xmlns="http://www.tei-c.org/ns/1.0">
   <biblFull>
      <titleStmt>
         <title>Two sermons the first preacht at Steeple-Aston in Oxfordshire at the funerall of Mr. Francis Croke of that place Aug. 2, 1672, the other at the funerall of Alexander Croke of Studley, Esq., buryed at Chilton in Buckinghamshire Octob. 24, 1672 / by Daniel Greenwood ...</title>
         <author>Greenwood, Daniel, 1627 or 8-1679.</author>
      </titleStmt>
      <extent>[3], 20, 17 p.   </extent>
      <publicationStmt>
         <publisher>[s.n.],</publisher>
         <pubPlace>Oxford :</pubPlace>
         <date when="1680">1680.</date>
      </publicationStmt>
      <notesStmt>
         <note>Reproduction of original in Union Theological Seminary Library, New York.</note>
      </notesStmt>
   </biblFull>
</sourceDesc>
