<?xml-model href="../schema/ep_sourceDesc.rnc" type="application/relax-ng-compact-syntax"?>
<sourceDesc xmlns="http://www.tei-c.org/ns/1.0">
  <biblFull>
    <titleStmt>
      <title>A looking-glass for loyalty, or, The subjects duty to his soveraign being the substance of several sermons preached by a person who always looked upon his allegiance as incorporated into his religion ...</title>
      <author>Higham, John, 17th cent.</author>
    </titleStmt>
    <extent>[16], 190 p.   </extent>
    <publicationStmt>
      <publisher>Printed for <persName type="publisher">Henry Brome</persName> ...,</publisher>
      <pubPlace>London :</pubPlace>
      <date when="1675">1675.</date>
    </publicationStmt>
    <notesStmt>
      <note>Epistle dedicatory signed: John Higham.</note>
      <note>Errata: p. [16].</note>
      <note>Reproduction of original in Bodleian Library.</note>
      <note>Marginal notes.</note>
    </notesStmt>
  </biblFull>
  <listPerson>
    <person type="publisher">
      <persName>Henry Brome</persName>
    </person>
  </listPerson>
</sourceDesc>
