<?xml-model href="../schema/sourceDesc_fragment.rnc" type="application/relax-ng-compact-syntax"?>
<sourceDesc xmlns="http://www.tei-c.org/ns/1.0">
   <biblFull>
      <titleStmt>
         <title>The speech of His Grace the Duke of Lauderdale, His Majesties high-commissioner from the kingdom of Scotland, to the Parliament there, the twelfth of November, 1673</title>
         <author>Lauderdale, John Maitland, Duke of, 1616-1682.</author>
      </titleStmt>
      <extent>7 p.   </extent>
      <publicationStmt>
         <publisher>Printed by Thomas Newcomb,</publisher>
         <pubPlace>[London] :</pubPlace>
         <date>1673.</date>
      </publicationStmt>
      <notesStmt>
         <note>"By His Majesties special command."</note>
         <note>Reproduction of original in the Bodleian Library.</note>
      </notesStmt>
   </biblFull>
</sourceDesc>
