<?xml-model href="../schema/sourceDesc_fragment.rnc" type="application/relax-ng-compact-syntax"?>
<sourceDesc xmlns="http://www.tei-c.org/ns/1.0">
  <biblFull>
    <titleStmt>
      <title>The mystery of atheism, or, The devices made use of to countenance and propagate it together with the evil and danger of them, set forth in several letters to a friend : wherein is made appear, that 'tis not want of evidence, but sincerity that makes men atheists / by the author of the Mystery of phanaticism.</title>
      <author>A. B.</author>
    </titleStmt>
    <extent>[8], 128 p.   </extent>
    <publicationStmt>
      <publisher>Printed for <persName type="publisher">A.</persName> and <persName type="publisher">J. Churchil</persName> ... and sold by <persName type="bookseller">Rich. Gravell</persName> ...,</publisher>
      <pubPlace>London :</pubPlace>
      <date when="1699">1699.</date>
    </publicationStmt>
    <notesStmt>
      <note>All letters signed: A.B.</note>
      <note>Reproduction of original in the Huntington Library.</note>
    </notesStmt>
  </biblFull>
  <listPerson>
    <person type="publisher">
      <persName>A.</persName>
    </person>
    <person type="publisher">
      <persName>J. Churchil</persName>
    </person>
    <person type="bookseller">
      <persName>Rich. Gravell</persName>
    </person>
  </listPerson>
</sourceDesc>
