<?xml-model href="../schema/sourceDesc_fragment.rnc" type="application/relax-ng-compact-syntax"?>
<sourceDesc xmlns="http://www.tei-c.org/ns/1.0">
   <biblFull>
      <titleStmt>
         <title>Vindiciae epistolarum S. Ignatii autore Joanne Pearson ... ; accesserunt Isaaci Vossii Epistolae duae adversus David Blondellum.</title>
         <author>Pearson, John, 1613-1686.</author>
         <author>Vossius, Isaac, 1618-1689. Epistolae duae adversus David Blondellum.</author>
      </titleStmt>
      <extent>[21], 29, [3], 110, [2], 221, [7], 36, [14] p.   </extent>
      <publicationStmt>
         <publisher>Typis Joann. Hayes :</publisher>
         <publisher>Prostant Londini, apud Guil. Wells &amp; Rob. Scott ...,</publisher>
         <pubPlace>Cantabrigiae :</pubPlace>
         <date when="1671">1671.</date>
      </publicationStmt>
      <notesStmt>
         <note>Reproduction of original in Union Theological Seminary Library, New York.</note>
      </notesStmt>
   </biblFull>
</sourceDesc>
