<?xml-model href="../schema/sourceDesc_fragment.rnc" type="application/relax-ng-compact-syntax"?>
<sourceDesc xmlns="http://www.tei-c.org/ns/1.0">
  <biblFull>
    <titleStmt>
      <title>The last speech and prayer with other passages of Thomas Venner, the chief incourager and promoter of the late horrid rebellion immediately before his execution in Coleman-street on Saturday last being the 19th of Ianuary, 1660 : together with the names of the rest that were condemned for the same fact.</title>
      <author>Venner, Thomas, d. 1661.</author>
    </titleStmt>
    <extent>7, [1] p.   </extent>
    <publicationStmt>
      <publisher>[s.n.],</publisher>
      <pubPlace>London :</pubPlace>
      <date when="1660">1660.</date>
    </publicationStmt>
    <notesStmt>
      <note>Reproduction of original in the University of Illinois (Urbana-Champaign Campus). Library.</note>
    </notesStmt>
  </biblFull>
</sourceDesc>
