<?xml-model href="../schema/sourceDesc_fragment.rnc" type="application/relax-ng-compact-syntax"?>
<sourceDesc xmlns="http://www.tei-c.org/ns/1.0">
   <biblFull>
      <titleStmt>
         <title>Exceeding true and happy newes from Pomfret Castle. Beeing a perfect description of a great battaile, fought by Mr. Hotham, sonne to Sr. Iohn Hotham, with 300. horse and 500. foote, against the Lord Savill, and Sir Francis Nevill, with 1500. horse and foot, before the walls of Pomfret Castle. Oct. 7. Also declaring how the Lord Savill was wounded and above 200. of his men slaine in the fight.</title>
      </titleStmt>
      <extent>[8] p.   </extent>
      <publicationStmt>
         <publisher>Printed for Tho. Rider,</publisher>
         <pubPlace>London :</pubPlace>
         <date when="1642">Octob. 11. 1642.</date>
      </publicationStmt>
      <notesStmt>
         <note>Reproduction of the original in the British Library.</note>
      </notesStmt>
   </biblFull>
</sourceDesc>
