<?xml-model href="../schema/sourceDesc_fragment.rnc" type="application/relax-ng-compact-syntax"?>
<sourceDesc xmlns="http://www.tei-c.org/ns/1.0">
   <biblFull>
      <titleStmt>
         <title>Mercy in her exaltation. Or, A soveraigne antidote against fear of the second death. In a sermon preached at the funeral of Daniel Taylor Esq; in Stephens Colemanstreet London, on the twentieth day of April, an. 1655.</title>
         <author>Goodwin, John, 1594?-1665.</author>
      </titleStmt>
      <extent>[12], 56 p.   </extent>
      <publicationStmt>
         <publisher>Printed by J. Macock, for H. Eversden, and are to be sold at his shop at the signe of the Grey-hound, in Paul's Churchyard.,</publisher>
         <pubPlace>London, :</pubPlace>
         <date when="1655">1655.</date>
      </publicationStmt>
      <notesStmt>
         <note>Dedication signed: John Goodvvin.</note>
         <note>Annotation on Thomason copy: "July. 20.".</note>
         <note>Reproduction of the original in the British Library.</note>
      </notesStmt>
   </biblFull>
</sourceDesc>
