<?xml-model href="../schema/sourceDesc_fragment.rnc" type="application/relax-ng-compact-syntax"?>
<sourceDesc xmlns="http://www.tei-c.org/ns/1.0">
   <biblFull>
      <titleStmt>
         <title>Quæstiones in sacra theologia discutiendæ Oxonii in vesperiis, nono die mensis Julii, An. Dom. 1664</title>
         <author>University of Oxford.</author>
      </titleStmt>
      <extent>1 sheet ([1] p.)   </extent>
      <publicationStmt>
         <publisher>Typis Lichfieldianis, Academiæ Typog.,</publisher>
         <pubPlace>Oxoniæ :</pubPlace>
         <date>Ann. Dom. 1664.</date>
      </publicationStmt>
      <notesStmt>
         <note>Reproduction of original in: Bodleian Library, Oxford, England.</note>
      </notesStmt>
   </biblFull>
</sourceDesc>
