<?xml-model href="../schema/sourceDesc_fragment.rnc" type="application/relax-ng-compact-syntax"?>
<sourceDesc xmlns="http://www.tei-c.org/ns/1.0">
  <biblFull>
    <titleStmt>
      <title>The speech of Their Excellencies the Lords Ambassadours Extraordinarie from the high and mighty States General of the Vnited Provinces of the Netherlands, taking their leave of both the Honourable Houses of Parliament assembled at Westminster. April the 10th. 1645. Translated out of French into English: and printed by their Excellencies order. Steph. Taylor. Secr.</title>
    </titleStmt>
    <extent>1 sheet ([1] p.)   </extent>
    <publicationStmt>
      <publisher>Printed by <persName type="printer">T. Badger</persName>,</publisher>
      <pubPlace>London :</pubPlace>
      <date when="1645">1645.</date>
    </publicationStmt>
    <notesStmt>
      <note>Annotation on Thomason copy: "Aprill 15:".</note>
      <note>Reproduction of the original in the British Library.</note>
    </notesStmt>
  </biblFull>
  <listPerson>
    <person type="printer">
      <persName>T. Badger</persName>
    </person>
  </listPerson>
</sourceDesc>
