<?xml-model href="../schema/sourceDesc_fragment.rnc" type="application/relax-ng-compact-syntax"?>
<sourceDesc xmlns="http://www.tei-c.org/ns/1.0">
  <biblFull>
    <titleStmt>
      <title>A nicke for neuters. A most godly and fruitfull sermon, begun and preached at Paules Crosse, the 30. day of October last, and continued &amp; finished in Paules Church, on New-yeeres day at night. / By Thomas Burt, Preacher of the Word.</title>
      <author>Burt, Thomas, preacher of the word.</author>
    </titleStmt>
    <extent>[85] p.   </extent>
    <publicationStmt>
      <publisher>Printed by <persName type="printer">Simon Stafford.</persName>,</publisher>
      <pubPlace>At London :</pubPlace>
      <date>1604.</date>
    </publicationStmt>
    <notesStmt>
      <note>Signatures: [par.]&#8312;, A-D&#8312;, E&#179;.</note>
      <note>Reproduction of original in: Folger Shakespeare Library.</note>
    </notesStmt>
  </biblFull>
  <listPerson>
    <person type="printer">
      <persName>Simon Stafford.</persName>
    </person>
  </listPerson>
</sourceDesc>
