<?xml-model href="../schema/sourceDesc_fragment.rnc" type="application/relax-ng-compact-syntax"?>
<sourceDesc xmlns="http://www.tei-c.org/ns/1.0">
  <biblFull>
    <titleStmt>
      <title>The guardian's instruction, or, The gentleman's romance. Written for the diversion and service of the gentry; particularly those educated in Cambridge and Oxford.</title>
      <author>Penton, Stephen, 1639-1706.</author>
    </titleStmt>
    <editionStmt>
      <edition>The second edition.</edition>
    </editionStmt>
    <extent>[14], 90, [2] p.   </extent>
    <publicationStmt>
      <publisher>Printed for <persName type="publisher">the author</persName>,</publisher>
      <pubPlace>London :</pubPlace>
      <date when="1697">1697.</date>
    </publicationStmt>
    <notesStmt>
      <note>Attributed to Stephen Penton.  Cf. Wing (2nd ed.).</note>
      <note>Imperfect: some pages have faded print.</note>
      <note>Includes index.</note>
      <note>Reproduction of original in: Bodleian Library.</note>
    </notesStmt>
  </biblFull>
  <listPerson>
    <person type="publisher">
      <persName>the author</persName>
    </person>
  </listPerson>
</sourceDesc>
