<?xml version="1.0" encoding="UTF-8"?><?xml-model href="../schema/ep_teiHeader.rng" type="application/xml" schematypens="http://relaxng.org/ns/structure/1.0"?><teiHeader xmlns="http://www.tei-c.org/ns/1.0">
  <fileDesc>
    <titleStmt>
      <title>A spirituall hymne or The sacrifice of a sinner to be offred vpon the altar of a humbled heart, to Christ our Redeemer. Inverted in English sapphicks, from the Latine, of the reverend, religious, and learned divine, Mr Robert Boyd of Trocborege. By Sr William Mure yo: of Rowallane knight. By whom is also annexed a poeme, entituled Doomes-day. Containing, hells horrour, and heavens happinesse.</title>
      <title>Roberti Boddii a Trochoregia Hecatombe christiana. English</title>
      <author>Boyd, Robert, 1578-1627.</author>
    </titleStmt>
    <publicationStmt>
      <publisher>EarlyPrint project</publisher>
      <idno type="tcpid">A16534</idno>
      <idno type="estcid">S116400</idno>
    </publicationStmt>
    <sourceDesc>
      <biblFull>
        <titleStmt>
          <title>A spirituall hymne or The sacrifice of a sinner to be offred vpon the altar of a humbled heart, to Christ our Redeemer. Inverted in English sapphicks, from the Latine, of the reverend, religious, and learned divine, Mr Robert Boyd of Trocborege. By Sr William Mure yo: of Rowallane knight. By whom is also annexed a poeme, entituled Doomes-day. Containing, hells horrour, and heavens happinesse.</title>
          <title>Roberti Boddii a Trochoregia Hecatombe christiana. English</title>
          <author gender="M">Boyd, Robert, 1578-1627.</author>
          <author gender="M">Mure, William, Sir, 1594-1657.</author>
        </titleStmt>
        <extent>[60] p.   </extent>
        <publicationStmt>
          <publisher>Printed by <persName type="printer">Iohn Wreittoun</persName>, and are to bee sold at <placeName>his shop alitle beneath the salt-Trorre</placeName>,</publisher>
          <pubPlace>Edinburgh :</pubPlace>
          <date when="1628">Anno Dom. 1628.</date>
        </publicationStmt>
        <notesStmt>
          <note>A translation, by Sir William Mure, of: Boyd, Robert. Roberti Boddii a Trochoregia Hecatombe christiana.</note>
          <note>"Doomes-day" has caption title on B3r.</note>
          <note>Signatures: A-C D⁶.</note>
          <note>Reproduction of the original in the National Library of Scotland.</note>
        </notesStmt>
      </biblFull>
      <listPerson type="tcp_ep">
        <person type="printer">
          <persName>Iohn Wreittoun</persName>
        </person>
      </listPerson>
      <listPerson type="estc_ep">
        <person role="creator">
          <persName>Boyd, Robert,</persName>
          <birth>1578</birth>
          <death>1627.</death>
          <sex value="M"/>
    </person>
        <person role="added" type="tr.">
          <persName>Mure, William, <roleName>Sir,</roleName></persName>
          <birth>1594</birth>
          <death>1567,</death>
          <sex value="M"/>
    </person>
      </listPerson>
    </sourceDesc>
  </fileDesc>
  <profileDesc>
    <textClass>
      <keywords n="general">
        <list>
          <item n="650a">Hymns, English</item>
        </list>
      </keywords>
      <keywords n="geographic">
        <list>
          <item n="752a">Great Britain</item>
          <item n="752b">Scotland</item>
          <item n="752d">Edinburgh.</item>
        </list>
      </keywords>
    </textClass>
  </profileDesc>
</teiHeader>