<?xml version="1.0" encoding="UTF-8"?><?xml-model href="../schema/ep_teiHeader.rng" type="application/xml" schematypens="http://relaxng.org/ns/structure/1.0"?><teiHeader xmlns="http://www.tei-c.org/ns/1.0">
  <fileDesc>
    <titleStmt>
      <title>By the Queene. A proclamation to represse all piracies and depredations vpon the seas</title>
      <author gender="F">England and Wales. Sovereign (1558-1603 : Elizabeth I)</author>
    </titleStmt>
    <publicationStmt>
      <publisher>EarlyPrint project</publisher>
      <idno type="tcpid">A21711</idno>
      <idno type="estcid">S112287</idno>
    </publicationStmt>
    <sourceDesc>
      <biblFull>
        <titleStmt>
          <title>By the Queene. A proclamation to represse all piracies and depredations vpon the seas</title>
          <author gender="F">England and Wales. Sovereign (1558-1603 : Elizabeth I)</author>
        </titleStmt>
        <extent>1 sheet ([1] p.)   </extent>
        <publicationStmt>
          <publisher>in <placeName>Powles Churchyarde</placeName> by <persName type="printer">Richarde Iugge</persName> and <persName type="printer">John Cawood</persName>, Printers to <persName type="patron">the Queenes Maiestie</persName>,</publisher>
          <pubPlace>Imprinted at London :</pubPlace>
          <date when="1569">[1569]</date>
        </publicationStmt>
        <notesStmt>
          <note>A proclamation forbidding intercourse with pirates and calling for their repression.</note>
          <note>Publication date from STC.</note>
          <note>At foot of sheet: Cum priuilegio Regiæ Maiestatis.</note>
          <note>Item at reel 2062:11b bound with STC 8014.3.</note>
          <note>Reproductions of originals in the Bodleian Library and Folger Shakespeare Library.</note>
        </notesStmt>
      </biblFull>
      <listPerson type="tcp_ep">
        <person type="printer">
          <persName>John Cawood</persName>
        </person>
        <person type="printer">
          <persName>Richarde Iugge</persName>
        </person>
        <person type="patron">
          <persName>the Queenes Maiestie</persName>
        </person>
      </listPerson>
      <listOrg type="estc_ep">
        <org>
          <orgName>
            <name>England and Wales.</name>
            <name>Sovereign (1558-1603 : Elizabeth I)</name>
          </orgName>
        </org>
      </listOrg>
    </sourceDesc>
  </fileDesc>
  <profileDesc>
    <textClass>
      <keywords n="general">
        <list>
          <item n="650a">Broadsides</item>
          <item n="650a">Pirates</item>
          <item n="651x">Proclamations</item>
          <item n="651x">History</item>
        </list>
      </keywords>
      <keywords n="temporal">
        <list>
          <item n="651y">Elizabeth, 1558-1603</item>
        </list>
      </keywords>
      <keywords n="geographic">
        <list>
          <item n="650z 651a 752b">England</item>
          <item n="651a 752a">Great Britain</item>
          <item n="752d">London.</item>
        </list>
      </keywords>
    </textClass>
  </profileDesc>
</teiHeader>