<?xml version="1.0" encoding="UTF-8"?><?xml-model href="../schema/ep_teiHeader.rng" type="application/xml" schematypens="http://relaxng.org/ns/structure/1.0"?><teiHeader xmlns="http://www.tei-c.org/ns/1.0">
  <fileDesc>
    <titleStmt>
      <title>The best treasure, or, The way to be truly rich being a discourse on Ephes. 3.8, wherein is opened and commended to saints and sinners the personal and purchased riches of Christ, as the best treasure, to be pursu'd and ensur'd by all that would be happy here and hereafter / by Bartholomew Ashwood.</title>
      <author>Ashwood, Bartholomew, 1622-1680.</author>
    </titleStmt>
    <publicationStmt>
      <publisher>EarlyPrint project</publisher>
      <idno type="tcpid">A26034</idno>
      <idno type="estcid">R16623</idno>
    </publicationStmt>
    <sourceDesc>
      <biblFull>
        <titleStmt>
          <title>The best treasure, or, The way to be truly rich being a discourse on Ephes. 3.8, wherein is opened and commended to saints and sinners the personal and purchased riches of Christ, as the best treasure, to be pursu'd and ensur'd by all that would be happy here and hereafter / by Bartholomew Ashwood.</title>
          <author gender="M">Ashwood, Bartholomew, 1622-1680.</author>
        </titleStmt>
        <extent>[6], 437, [9] p.   </extent>
        <publicationStmt>
          <publisher>Printed for <persName type="publisher">William Marshall</persName> ...,</publisher>
          <pubPlace>London :</pubPlace>
          <date when="1681">1681.</date>
        </publicationStmt>
        <notesStmt>
          <note>Pages 353-356 are stained with loss of text in filmed copy.  Pages 340-end photographed from Bodleian Library copy and inserted at end.</note>
          <note>Reproduction of original in Union Theological Seminary Library, New York.</note>
        </notesStmt>
      </biblFull>
      <listPerson type="tcp_ep">
        <person type="publisher">
          <persName>William Marshall</persName>
        </person>
      </listPerson>
      <listPerson type="estc_ep">
        <person role="creator">
          <persName>Ashwood, Bartholomew,</persName>
          <birth>1622</birth>
          <death>1680.</death>
          <sex value="M"/>
    </person>
        <person role="added">
          <persName>Owen, John,</persName>
          <birth>1616</birth>
          <death>1683.</death>
          <sex value="M"/>
    </person>
      </listPerson>
    </sourceDesc>
  </fileDesc>
  <profileDesc>
    <textClass>
      <keywords n="general">
        <list>
          <item n="650a">Christian life</item>
        </list>
      </keywords>
      <keywords n="geographic">
        <list>
          <item n="752a">Great Britain</item>
          <item n="752b">England</item>
          <item n="752d">London.</item>
        </list>
      </keywords>
    </textClass>
  </profileDesc>
</teiHeader>