<?xml version="1.0" encoding="UTF-8"?><?xml-model href="../schema/ep_teiHeader.rng" type="application/xml" schematypens="http://relaxng.org/ns/structure/1.0"?><teiHeader xmlns="http://www.tei-c.org/ns/1.0">
  <fileDesc>
    <titleStmt>
      <title>An essay of transmigration, in defence of Pythagoras, or, A discourse of natural philosophy</title>
      <author>Bulstrode, Whitelocke, 1650-1724.</author>
    </titleStmt>
    <publicationStmt>
      <publisher>EarlyPrint project</publisher>
      <idno type="tcpid">A30096</idno>
      <idno type="estcid">R16493</idno>
    </publicationStmt>
    <sourceDesc>
      <biblFull>
        <titleStmt>
          <title>An essay of transmigration, in defence of Pythagoras, or, A discourse of natural philosophy</title>
          <author gender="M">Bulstrode, Whitelocke, 1650-1724.</author>
        </titleStmt>
        <extent>[56], 192 p.   </extent>
        <publicationStmt>
          <publisher>Printed by <persName type="printer">E.H.</persName> for <persName type="publisher">Tho. Basset</persName> ...,</publisher>
          <pubPlace>London :</pubPlace>
          <date when="1692">1692.</date>
        </publicationStmt>
        <notesStmt>
          <note>Reproduction of original in Huntington Library.</note>
          <note>Epistle dedicatory signed: Whitelocke Bulstrode.</note>
          <note>Attributed to Whitlocke Bulstrode. cf. BM.</note>
          <note>Table of contents: p. [45]-[54]</note>
        </notesStmt>
      </biblFull>
      <listPerson type="tcp_ep">
        <person type="publisher">
          <persName>Tho. Basset</persName>
        </person>
        <person type="printer">
          <persName>E.H.</persName>
        </person>
      </listPerson>
      <listPerson type="estc_ep">
        <person role="creator">
          <persName>Bulstrode, Whitelocke,</persName>
          <birth>1650</birth>
          <death>1724.</death>
          <sex value="M"/>
    </person>
        <person role="subject">
          <persName>Pythagoras</persName>
          <sex value="M"/>
    </person>
        <person role="added" type="engraver.">
          <persName>Elder, William,</persName>
          <floruit>active 1680,</floruit>
          <sex value="M"/>
    </person>
      </listPerson>
    </sourceDesc>
  </fileDesc>
  <profileDesc>
    <textClass>
      <keywords n="general">
        <list>
          <item n="650a">Pythagoras and Pythagorean school</item>
          <item n="650a">Transmigration</item>
        </list>
      </keywords>
      <keywords n="geographic">
        <list>
          <item n="752a">Great Britain</item>
          <item n="752b">England</item>
          <item n="752d">London.</item>
        </list>
      </keywords>
    </textClass>
  </profileDesc>
</teiHeader>