<?xml version="1.0" encoding="UTF-8"?><?xml-model href="../schema/ep_teiHeader.rng" type="application/xml" schematypens="http://relaxng.org/ns/structure/1.0"?><teiHeader xmlns="http://www.tei-c.org/ns/1.0">
  <fileDesc>
    <titleStmt>
      <title>A proclamation anent pedagogues, chaplains and others</title>
      <author>England and Wales. Sovereign (1660-1685 : Charles II)</author>
    </titleStmt>
    <publicationStmt>
      <publisher>EarlyPrint project</publisher>
      <idno type="tcpid">A58712</idno>
      <idno type="estcid">R2452</idno>
    </publicationStmt>
    <sourceDesc>
      <biblFull>
        <titleStmt>
          <title>A proclamation anent pedagogues, chaplains and others</title>
          <author>England and Wales. Sovereign (1660-1685 : Charles II)</author>
          <author gender="M">Charles II, King of England, 1630-1685.</author>
        </titleStmt>
        <extent>1 sheet ([1] p.)   </extent>
        <publicationStmt>
          <publisher>Printed by <persName type="printer">the heir of Andrew Anderson</persName> ... ;</publisher>
          <publisher>Reprinted by George Croom,</publisher>
          <pubPlace>Edinbvrgh :</pubPlace>
          <pubPlace>[London] :</pubPlace>
          <date when="1683">1683.</date>
        </publicationStmt>
        <notesStmt>
          <note>Broadside.</note>
          <note>"Per actum dominorum secreti concilij. Wil. Paterson, Cls. Sti. Concilij."</note>
          <note>Reproductions of original in Bodleian Library.</note>
          <note>Item at reel 760:28 identified as Wing C3229A (number cancelled).</note>
        </notesStmt>
      </biblFull>
      <listPerson type="tcp_ep">
        <person type="printer">
          <persName>the heir of Andrew Anderson</persName>
        </person>
      </listPerson>
      <listPerson type="estc_ep">
        <person role="added">
          <persName>Charles <roleName>King of England,</roleName> <genName>II,</genName></persName>
          <birth>1630</birth>
          <death>1685.</death>
        </person>
      </listPerson>
      <listOrg type="estc_ep">
        <org>
          <orgName>
            <name>Scotland.</name>
            <name>Sovereign (1660-1685 : Charles II)</name>
          </orgName>
        </org>
      </listOrg>
    </sourceDesc>
  </fileDesc>
  <profileDesc>
    <textClass>
      <keywords n="general">
        <list>
          <item n="650a">Education</item>
          <item n="650a">Dissenters, Religious</item>
          <item n="651x">History</item>
        </list>
      </keywords>
      <keywords n="temporal">
        <list>
          <item n="651y">1660-1688</item>
        </list>
      </keywords>
      <keywords n="geographic">
        <list>
          <item n="650z 651a">Scotland</item>
          <item n="752a">Great Britain</item>
          <item n="752b">England</item>
          <item n="752d">London.</item>
        </list>
      </keywords>
    </textClass>
  </profileDesc>
</teiHeader>