<?xml version="1.0" encoding="UTF-8"?><?xml-model href="../schema/ep_teiHeader.rng" type="application/xml" schematypens="http://relaxng.org/ns/structure/1.0"?><teiHeader xmlns="http://www.tei-c.org/ns/1.0">
  <fileDesc>
    <titleStmt>
      <title>A genealogical history of the kings of England, and monarchs of Great Britain, &amp;c. from the conquest, anno 1066 to the year, 1677 in seven parts or books, containing a discourse of their several lives, marriages, and issues, times of birth, death, places of burial, and monumental inscriptions : with their effigies, seals, tombs, cenotaphs, devises, arms, quarterings, crests, and supporters : all engraven in copper plates / furnished with several remarques and annotations by Francis Sanford, Esq. ...</title>
      <author gender="M">Sandford, Francis, 1630-1694.</author>
      <author gender="M">King, Gregory, 1648-1712.</author>
      <author gender="M">Gaywood, Richard, fl. 1650-1680.</author>
      <author gender="M">Barlow, Francis, 1626?-1702.</author>
      <author gender="M">Hollar, Wenceslaus, 1607-1677.</author>
    </titleStmt>
    <publicationStmt>
      <publisher>EarlyPrint project</publisher>
      <idno type="tcpid">A62149</idno>
      <idno type="estcid">R8565</idno>
    </publicationStmt>
    <sourceDesc>
      <biblFull>
        <titleStmt>
          <title>A genealogical history of the kings of England, and monarchs of Great Britain, &amp;c. from the conquest, anno 1066 to the year, 1677 in seven parts or books, containing a discourse of their several lives, marriages, and issues, times of birth, death, places of burial, and monumental inscriptions : with their effigies, seals, tombs, cenotaphs, devises, arms, quarterings, crests, and supporters : all engraven in copper plates / furnished with several remarques and annotations by Francis Sanford, Esq. ...</title>
          <author gender="M">Sandford, Francis, 1630-1694.</author>
          <author gender="M">King, Gregory, 1648-1712.</author>
          <author gender="M">Gaywood, Richard, fl. 1650-1680.</author>
          <author gender="M">Barlow, Francis, 1626?-1702.</author>
          <author gender="M">Hollar, Wenceslaus, 1607-1677.</author>
        </titleStmt>
        <extent>[13], 578 [i.e. 590], [11] p., 5 leaves of folded plates : ill., geneal. tables.  </extent>
        <publicationStmt>
          <publisher>Printed by <persName type="printer">Tho. Newcomb</persName> for <persName type="publisher">the author</persName>,</publisher>
          <pubPlace>[London] In the Savoy :</pubPlace>
          <date when="1677">1677.</date>
        </publicationStmt>
        <notesStmt>
          <note>First edition.</note>
          <note>"A table" [i.e. index]: p. [1]-[10] at end.</note>
          <note>Errata: p. [11] at end.</note>
          <note>The author was assisted by Gregory King.</note>
          <note>Engravings by Richard Gaywood, Francis Barlow, and Wenceslaus Hollar.</note>
          <note>Reproduction of original in Huntington Library.</note>
        </notesStmt>
      </biblFull>
      <listPerson type="tcp_ep">
        <person type="publisher">
          <persName>the author</persName>
        </person>
        <person type="printer">
          <persName>Tho. Newcomb</persName>
        </person>
      </listPerson>
      <listPerson type="estc_ep">
        <person role="creator">
          <persName>Sandford, Francis,</persName>
          <birth>1630</birth>
          <death>1694.</death>
          <sex value="M"/>
    </person>
        <person role="added">
          <persName>Barlow, Francis,</persName>
          <birth>1626?</birth>
          <death>1702.</death>
          <sex value="M"/>
    </person>
        <person role="added">
          <persName>Gaywood, Richard,</persName>
          <floruit>active 1650-1680.</floruit>
          <sex value="M"/>
    </person>
        <person role="added">
          <persName>Hollar, Wenceslaus,</persName>
          <birth>1607</birth>
          <death>1677.</death>
          <sex value="M"/>
    </person>
        <person role="added">
          <persName>King, Gregory,</persName>
          <birth>1648</birth>
          <death>1712.</death>
          <sex value="M"/>
    </person>
      </listPerson>
    </sourceDesc>
  </fileDesc>
  <profileDesc>
    <textClass>
      <keywords n="general">
        <list>
          <item n="651x">History</item>
        </list>
      </keywords>
      <keywords n="temporal">
        <list>
          <item n="651y">1066-1687</item>
        </list>
      </keywords>
      <keywords n="geographic">
        <list>
          <item n="651a 752a">Great Britain</item>
          <item n="752b">England</item>
          <item n="752d">London.</item>
        </list>
      </keywords>
    </textClass>
  </profileDesc>
</teiHeader>