<?xml version="1.0" encoding="UTF-8"?><?xml-model href="../schema/ep_teiHeader.rng" type="application/xml" schematypens="http://relaxng.org/ns/structure/1.0"?><teiHeader xmlns="http://www.tei-c.org/ns/1.0">
  <fileDesc>
    <titleStmt>
      <title>The country-man's companion, or, A new method of ordering horses &amp; sheep so as to preserve them both from diseases and causalties [sic], or, to recover them if fallen ill and also to render them much more serviceable and useful to their owners, than has yet been discovered, known or practised : and particularly to preserve sheep from that monsterous, mortifying distemper, the rot / by Philotheos Physiologus, the author of The way to health, long life and happiness, &amp;c.</title>
      <author>Tryon, Thomas, 1634-1703.</author>
    </titleStmt>
    <publicationStmt>
      <publisher>EarlyPrint project</publisher>
      <idno type="tcpid">A63788</idno>
      <idno type="estcid">R23567</idno>
    </publicationStmt>
    <sourceDesc>
      <biblFull>
        <titleStmt>
          <title>The country-man's companion, or, A new method of ordering horses &amp; sheep so as to preserve them both from diseases and causalties [sic], or, to recover them if fallen ill and also to render them much more serviceable and useful to their owners, than has yet been discovered, known or practised : and particularly to preserve sheep from that monsterous, mortifying distemper, the rot / by Philotheos Physiologus, the author of The way to health, long life and happiness, &amp;c.</title>
          <author gender="M">Tryon, Thomas, 1634-1703.</author>
        </titleStmt>
        <extent>[8], 173, [3] p.   </extent>
        <publicationStmt>
          <publisher>Printed and sold by <persName type="printer"><persName type="bookseller">Andrew Sowle</persName></persName> ...,</publisher>
          <pubPlace>London :</pubPlace>
          <date when="1684">[1684]</date>
        </publicationStmt>
        <notesStmt>
          <note>Advertisement: p. [1]-[3] at end.</note>
          <note>Reproduction of original in Bodleian Library.</note>
        </notesStmt>
      </biblFull>
      <listPerson type="tcp_ep">
        <person type="printer">
          <persName>Andrew Sowle</persName>
        </person>
        <person type="bookseller">
          <persName>Andrew Sowle</persName>
        </person>
      </listPerson>
      <listPerson type="estc_ep">
        <person role="creator">
          <persName>Tryon, Thomas,</persName>
          <birth>1634</birth>
          <death>1703.</death>
          <sex value="M"/>
    </person>
      </listPerson>
    </sourceDesc>
  </fileDesc>
  <profileDesc>
    <textClass>
      <keywords n="general">
        <list>
          <item n="650a">Animals, Treatment of</item>
          <item n="650a">Communicable diseases in animals</item>
          <item n="650a">Conduct of life</item>
          <item n="651x">Description and travel</item>
          <item n="651x">Emigration and immigration</item>
        </list>
      </keywords>
      <keywords n="form">
        <list>
          <item n="650v">Early works to 1900.</item>
        </list>
      </keywords>
      <keywords n="geographic">
        <list>
          <item n="651a">New Jersey</item>
          <item n="651a">Pennsylvania</item>
          <item n="752a">Great Britain</item>
          <item n="752b">England</item>
          <item n="752d">London.</item>
        </list>
      </keywords>
    </textClass>
  </profileDesc>
</teiHeader>