<?xml version="1.0" encoding="UTF-8"?><?xml-model href="../schema/ep_teiHeader.rng" type="application/xml" schematypens="http://relaxng.org/ns/structure/1.0"?><teiHeader xmlns="http://www.tei-c.org/ns/1.0">
  <fileDesc>
    <titleStmt>
      <title>A discourse concerning the beauty of providence in all the rugged passages of it very seasonable to quiet and support the heart in these times of publick confusion / by John Wilkins ...</title>
      <title>Sermons. Selections</title>
      <author>Wilkins, John, 1614-1672.</author>
    </titleStmt>
    <publicationStmt>
      <publisher>EarlyPrint project</publisher>
      <idno type="tcpid">A66025</idno>
      <idno type="estcid">R1664</idno>
    </publicationStmt>
    <sourceDesc>
      <biblFull>
        <titleStmt>
          <title>A discourse concerning the beauty of providence in all the rugged passages of it very seasonable to quiet and support the heart in these times of publick confusion / by John Wilkins ...</title>
          <title>Sermons. Selections</title>
          <author gender="M">Wilkins, John, 1614-1672.</author>
        </titleStmt>
        <extent>[22], 119 p.   </extent>
        <publicationStmt>
          <publisher>Printed for <persName type="publisher">Sa. Gellibrand</persName> ...,</publisher>
          <pubPlace>London :</pubPlace>
          <date when="1649">1649.</date>
        </publicationStmt>
        <notesStmt>
          <note>Reproduction of original in Cambridge University Library.</note>
        </notesStmt>
      </biblFull>
      <listPerson type="tcp_ep">
        <person type="publisher">
          <persName>Sa. Gellibrand</persName>
        </person>
      </listPerson>
      <listPerson type="estc_ep">
        <person role="creator">
          <persName>Wilkins, John,</persName>
          <birth>1614</birth>
          <death>1672.</death>
          <sex value="M"/>
    </person>
      </listPerson>
    </sourceDesc>
  </fileDesc>
  <profileDesc>
    <textClass>
      <keywords n="general">
        <list>
          <item n="650a">Natural theology</item>
        </list>
      </keywords>
      <keywords n="geographic">
        <list>
          <item n="752a">Great Britain</item>
          <item n="752b">England</item>
          <item n="752d">London.</item>
        </list>
      </keywords>
    </textClass>
  </profileDesc>
</teiHeader>