<?xml version="1.0" encoding="UTF-8"?><?xml-model href="../schema/ep_teiHeader.rng" type="application/xml" schematypens="http://relaxng.org/ns/structure/1.0"?><teiHeader xmlns="http://www.tei-c.org/ns/1.0">
  <fileDesc>
    <titleStmt>
      <title>By the King and Queen, a proclamation for a general fast</title>
      <author>England and Wales. Sovereign (1689-1694 : William and Mary)</author>
    </titleStmt>
    <publicationStmt>
      <publisher>EarlyPrint project</publisher>
      <idno type="tcpid">A66280</idno>
      <idno type="estcid">R38078</idno>
    </publicationStmt>
    <sourceDesc>
      <biblFull>
        <titleStmt>
          <title>By the King and Queen, a proclamation for a general fast</title>
          <author>England and Wales. Sovereign (1689-1694 : William and Mary)</author>
          <author gender="F">Mary II, Queen of England, 1662-1694.</author>
          <author gender="M">William III, King of England, 1650-1702.</author>
        </titleStmt>
        <extent>1 broadside.   </extent>
        <publicationStmt>
          <publisher>Printed by <persName type="printer">Charles Bill</persName> and <persName type="printer">Thomas Newcomb</persName> ...,</publisher>
          <pubPlace>London :</pubPlace>
          <date when="1689">1689.</date>
        </publicationStmt>
        <notesStmt>
          <note>"Given at our court at Hampton-Court, this 23rd day of May, 1689. In the first year of our reign.</note>
          <note>Reproduction of original in the Harvard University Library.</note>
        </notesStmt>
      </biblFull>
      <listPerson type="tcp_ep">
        <person type="printer">
          <persName>Charles Bill</persName>
        </person>
        <person type="printer">
          <persName><choice><orig>Thomas Newcomb</orig><reg>Newcomb, Thomas Junior, -1691</reg></choice></persName>
        </person>
      </listPerson>
      <listPerson type="estc_ep">
        <person role="added">
          <persName>Mary <roleName>Queen of England,</roleName> <genName>II,</genName></persName>
          <birth>1662</birth>
          <death>1694.</death>
        </person>
        <person role="added">
          <persName>William <roleName>King of England,</roleName> <genName>III,</genName></persName>
          <birth>1650</birth>
          <death>1702.</death>
        </person>
      </listPerson>
      <listOrg type="estc_ep">
        <org>
          <orgName>
            <name>England and Wales.</name>
            <name>Sovereign (1689-1694 : William and Mary)</name>
          </orgName>
        </org>
      </listOrg>
    </sourceDesc>
  </fileDesc>
  <profileDesc>
    <textClass>
      <keywords n="general">
        <list>
          <item n="650a">Fasting</item>
          <item n="651x">History</item>
        </list>
      </keywords>
      <keywords n="temporal">
        <list>
          <item n="651y">William and Mary, 1689-1702</item>
        </list>
      </keywords>
      <keywords n="geographic">
        <list>
          <item n="651a 752a">Great Britain</item>
          <item n="752b">England</item>
          <item n="752d">London.</item>
        </list>
      </keywords>
    </textClass>
  </profileDesc>
</teiHeader>