<?xml version="1.0" encoding="UTF-8"?><?xml-model href="../schema/ep_teiHeader.rng" type="application/xml" schematypens="http://relaxng.org/ns/structure/1.0"?><teiHeader xmlns="http://www.tei-c.org/ns/1.0">
  <fileDesc>
    <titleStmt>
      <title>A wonderful instance of God's appearance for, and presence with his people in a day of suffering, or, A narrative of the most holy life, and triumphant death of Mr. Fulcran Rey who was put to death in France, for being a publick preacher / in a letter from a friend, to a Protestant refugie ; with allowance, June 2, 1688.</title>
      <author>Friend.</author>
    </titleStmt>
    <publicationStmt>
      <publisher>EarlyPrint project</publisher>
      <idno type="tcpid">A66912</idno>
      <idno type="estcid">R20406</idno>
    </publicationStmt>
    <sourceDesc>
      <biblFull>
        <titleStmt>
          <title>A wonderful instance of God's appearance for, and presence with his people in a day of suffering, or, A narrative of the most holy life, and triumphant death of Mr. Fulcran Rey who was put to death in France, for being a publick preacher / in a letter from a friend, to a Protestant refugie ; with allowance, June 2, 1688.</title>
          <author>Friend.</author>
        </titleStmt>
        <extent>16 p.   </extent>
        <publicationStmt>
          <publisher>Printed for <persName type="publisher">Tho. Fabian</persName> ...,</publisher>
          <pubPlace>London :</pubPlace>
          <date when="1688">1688.</date>
        </publicationStmt>
        <notesStmt>
          <note>Reproduction of original in Huntington Library.</note>
        </notesStmt>
      </biblFull>
      <listPerson type="tcp_ep">
        <person type="publisher">
          <persName>Tho. Fabian</persName>
        </person>
      </listPerson>
      <listPerson type="estc_ep">
        <person role="creator">
          <persName>Friend.</persName>
          <sex value=""/>
    </person>
        <person role="subject">
          <persName>Rey, Fulcran,</persName>
          <floruit>1663 or 1664?-1688?</floruit>
          <sex value="M"/>
    </person>
      </listPerson>
    </sourceDesc>
  </fileDesc>
  <profileDesc>
    <textClass>
      <keywords n="general">
        <list>
          <item n="650a">Christian life</item>
          <item n="650a">Presence of God</item>
        </list>
      </keywords>
      <keywords n="geographic">
        <list>
          <item n="752a">Great Britain</item>
          <item n="752b">England</item>
          <item n="752d">London.</item>
        </list>
      </keywords>
    </textClass>
  </profileDesc>
</teiHeader>