<?xml version="1.0" encoding="UTF-8"?><?xml-model href="../schema/ep_teiHeader.rng" type="application/xml" schematypens="http://relaxng.org/ns/structure/1.0"?><teiHeader xmlns="http://www.tei-c.org/ns/1.0">
  <fileDesc>
    <titleStmt>
      <title>Aulicus his hue and cry sent forth after Britanicus, vvho is generally reported to be a lost man.</title>
      <author>Cheynell, Francis, 1608-1665.</author>
    </titleStmt>
    <publicationStmt>
      <publisher>EarlyPrint project</publisher>
      <idno type="tcpid">A79471</idno>
      <idno type="estcid">R200211</idno>
    </publicationStmt>
    <sourceDesc>
      <biblFull>
        <titleStmt>
          <title>Aulicus his hue and cry sent forth after Britanicus, vvho is generally reported to be a lost man.</title>
          <author gender="M">Cheynell, Francis, 1608-1665.</author>
        </titleStmt>
        <extent>[2], 6 p.   </extent>
        <publicationStmt>
          <publisher>[Bernard Alsop?],</publisher>
          <pubPlace>London: :</pubPlace>
          <date when="1645">Printed in the dismall year of Britanicus. 1645.</date>
        </publicationStmt>
        <notesStmt>
          <note>Attributed to Francis Cheynell.</note>
          <note>"Printed by Bernard Alsop"--Thomason Catalogue.</note>
          <note>Annotation on Thomason copy: "Aug: 13th".</note>
          <note>Reproduction of the original in the British Library.</note>
        </notesStmt>
      </biblFull>
      <listPerson type="estc_ep">
        <person role="creator">
          <persName>Cheynell, Francis,</persName>
          <birth>1608</birth>
          <death>1665.</death>
          <sex value="M"/>
    </person>
        <person role="added" n="attributed name">
          <persName>Birkenhead, John, <roleName>Sir,</roleName></persName>
          <birth>1616</birth>
          <death>1679,</death>
          <sex value="M"/>
    </person>
      </listPerson>
    </sourceDesc>
  </fileDesc>
  <profileDesc>
    <textClass>
      <keywords n="general">
        <list>
          <item n="651x">History</item>
          <item n="651x">Politics and government</item>
        </list>
      </keywords>
      <keywords n="temporal">
        <list>
          <item n="651y">Civil War, 1642-1649.</item>
          <item n="651y">1642-1649.</item>
        </list>
      </keywords>
      <keywords n="geographic">
        <list>
          <item n="651a 752a">Great Britain</item>
          <item n="752b">England</item>
          <item n="752d">London.</item>
        </list>
      </keywords>
    </textClass>
  </profileDesc>
</teiHeader>