<?xml version="1.0" encoding="UTF-8"?><?xml-model href="../schema/ep_teiHeader.rng" type="application/xml" schematypens="http://relaxng.org/ns/structure/1.0"?><teiHeader xmlns="http://www.tei-c.org/ns/1.0">
  <fileDesc>
    <titleStmt>
      <title>Daffy's original and famous Elixir salutis : the choice drink of health, or, health-bringing drink, being a famous cordial drink, found out by the providence of the almighty, and ... experiences by my self and other divers persons ... a most excellent preservative of mankind. A secret far beyond any medicament yet known ... the same being fitted unto all ages, sexes, complexions and constitutions ... / Never published by any but Anthony Daffy, and now by me Elias Daffy his son.</title>
      <author>Daffy, Anthony.</author>
    </titleStmt>
    <publicationStmt>
      <publisher>EarlyPrint project</publisher>
      <idno type="tcpid">B02630</idno>
      <idno type="estcid">R213391</idno>
    </publicationStmt>
    <sourceDesc>
      <biblFull>
        <titleStmt>
          <title>Daffy's original and famous Elixir salutis : the choice drink of health, or, health-bringing drink, being a famous cordial drink, found out by the providence of the almighty, and ... experiences by my self and other divers persons ... a most excellent preservative of mankind. A secret far beyond any medicament yet known ... the same being fitted unto all ages, sexes, complexions and constitutions ... / Never published by any but Anthony Daffy, and now by me Elias Daffy his son.</title>
          <author gender="M">Daffy, Anthony.</author>
          <author gender="M">Daffy, Elias.</author>
        </titleStmt>
        <extent>[8], 8 p.   </extent>
        <publicationStmt>
          <publisher>Printed with allowance for <persName type="publisher">the author</persName>,</publisher>
          <pubPlace>London :</pubPlace>
          <date when="1698">1698.</date>
        </publicationStmt>
        <notesStmt>
          <note>Imperfect: faded, torn with loss of text.</note>
          <note>Reproduction of original in: British Library.</note>
        </notesStmt>
      </biblFull>
      <listPerson type="tcp_ep">
        <person type="publisher">
          <persName>the author</persName>
        </person>
      </listPerson>
      <listPerson type="estc_ep">
        <person role="creator">
          <persName>Daffy, Anthony.</persName>
          <sex value="M"/>
    </person>
      </listPerson>
    </sourceDesc>
  </fileDesc>
  <profileDesc>
    <textClass>
      <keywords n="general">
        <list>
          <item n="650a">Medicine, Popular</item>
        </list>
      </keywords>
      <keywords n="form">
        <list>
          <item n="655a">Advertisements.</item>
        </list>
      </keywords>
      <keywords n="geographic">
        <list>
          <item n="752a">Great Britain</item>
          <item n="752b">England</item>
          <item n="752d">London.</item>
        </list>
      </keywords>
    </textClass>
  </profileDesc>
</teiHeader>